{"ecFactory_L1": {"KD": ["YIL066C", "YDL024C", "YOR245C", "YJL026W", "YKL120W", "YJR103W", "YFR053C", "YGR180C", "YGL080W", "YLR438W", "YGL253W", "YDL066W", "YDR148C", "YNR019W", "YBL039C", "YLR446W", "YDL100C", "YDR503C", "YGR243W", "YCL040W", "YMR241W", "YHR002W", "YHR162W", "YPL061W", "YLR146C", "YCR048W", "YER070W", "YIL125W", "YMR267W"], "OE": ["YJL198W", "YNR001C", "YGL062W", "YDR300C", "YBR132C", "YGR193C", "YNR013C", "YMR062C", "YOR283W", "YER069W", "YAL038W", "YGR121C", "YDR441C", "YPR069C", "YML123C", "YLL028W", "YPR118W", "YKL181W", "YKL184W", "YOL140W", "YLR180W", "YML120C", "YBR221C", "YJR024C", "YHR183W", "YOL052C", "YOR273C", "YMR009W", "YLR017W", "YEL038W", "YER099C", "YOL126C", "YNL241C", "YLR174W", "YPL274W", "YHR163W", "YGR254W", "YCR037C", "YOR323C", "YOR375C", "YBR296C", "YPR138C", "YHL016C", "YPR021C", "YNL142W", "YER178W", "YOR130C", "YNL071W", "YKL029C", "YNL036W", "YKL085W", "YOR095C", "YDR384C"]}, "ecFactory_L2": {"KD": ["YDL066W", "YCL040W", "YNR019W", "YPL061W", "YFR053C", "YLR446W", "YLR146C", "YDL024C", "YCR048W", "YDL100C", "YDR503C", "YOR245C", "YLR438W", "YGL253W", "YMR267W"], "OE": ["YDR441C", "YOR375C", "YPR069C", "YMR009W", "YKL181W", "YLR017W", "YEL038W", "YER099C", "YKL184W", "YNR001C", "YOL140W", "YGL062W", "YER178W", "YNL071W", "YKL029C", "YNL241C", "YLR180W", "YBR221C", "YJR024C", "YGR193C", "YHR183W", "YHR163W", "YOL052C", "YER069W", "YAL038W"]}, "ecFactory_L3": {"KD": ["YDL066W", "YCL040W", "YNR019W", "YPL061W", "YFR053C", "YLR446W", "YLR146C", "YDL024C", "YCR048W", "YDL100C", "YDR503C", "YOR245C", "YLR438W", "YGL253W", "YMR267W"], "OE": ["YPR069C", "YMR009W", "YLR017W", "YEL038W", "YKL184W", "YOL140W", "YJR024C", "YOL052C", "YER069W"]}, "fseof": {"KD": ["YCR048W", "YNR019W", "YOR245C", "YMR165C", "YBR006W", "YNL277W", "YLR446W", "YFL058W", "YPR121W", "YCL040W", "YGR019W", "YLR438W", "YOL055C", "YPL258C", "YPL214C", "YPL061W", "YFR053C", "YMR267W", "YGL253W", "YMR241W"], "OE": ["YOR192C", "YLR237W", "YMR170C", "YOR374W", "YGL008C", "YPL036W", "YER073W", "YOR071C", "YER005W", "YEL017C-A", "YOR143C", "YCR024C-A", "YMR110C", "YPR069C", "YHR137W", "YMR009W", "YOR273C", "YHL016C", "YDR441C", "YBR132C", "YPL274W", "YPR118W", "YOL052C", "YML022W", "YJR024C", "YEL038W", "YLL028W", "YLR017W", "YKL184W", "YOR136W", "YNL037C", "YKL029C", "YML123C", "YJL198W", "YNR013C", "YBR296C", "YCR037C", "YLR180W", "YDR502C", "YOL061W", "YKL181W", "YBL068W", "YHL011C", "YER099C", "YER069W", "YOL140W", "YMR062C", "YOR130C", "YLR174W", "YPR021C", "YOL126C", "YDR300C", "YOR323C", "YOR095C", "YPR001W", "YNR001C", "YKL085W", "YDR516C", "YGR256W", "YNL241C", "YGR248W", "YHR183W", "YHR163W", "YBR218C", "YGL062W", "YNL036W", "YNL142W", "YPR138C", "YGR121C", "YDR384C", "YGR193C", "YNL071W", "YBR221C", "YER178W", "YDR226W", "YOR375C", "YAL062W", "YOR347C", "YAL038W", "YML120C", "YOR283W", "YGR254W", "YHR174W", "YPL281C", "YOR393W", "YMR323W", "YKL152C"]}, "optforce": {"KD": ["YBL033C", "YMR113W", "YPL274W", "YGR267C", "YDR341C", "YJL166W", "YGR062C", "YGL245W", "YJL133W", "YLR328W", "YJR143C", "YDR487C", "YHR051W", "YOL143C", "YJR025C", "YHR116W", "YBL076C", "YHR019C", "YGR191W", "YDR023W", "YOR321W", "YPL172C", "YMR319C", "YDL093W", "YDR376W", "YGR143W", "YOR176W", "YPL252C", "YPL132W", "YOR278W", "YGR094W", "YOR168W", "YBL045C", "YMR256C", "YHR074W", "YHR011W", "YNL275W", "YPR081C", "YER141W", "YGL255W", "YBR256C", "YGR264C", "YEL039C", "YJL003W", "Q0105", "YDR456W", "YGL040C", "YHL016C", "YLL028W", "YDL045C", "Q0275", "Q0045", "YDL067C", "YDR529C", "YPL160W", "YDL055C", "YJL129C", "YMR058W", "YIL078W", "YGR010W", "YIL111W", "YLR395C", "YOR273C", "YPR159W", "YLR342W", "YLL018C-A", "YPR033C", "YDR231C", "YLR060W", "YNL256W", "YBR132C", "YOL097C", "GR191W", "YHR020W", "YBL098W", "YGR185C", "YKR039W", "YMR306W", "YJR048W", "YLR038C", "YHR001W-A", "YFL022C", "YDR047W", "YGR032W", "YGL187C", "YBR121C", "YNL052W", "YLL018C", "YPR183W", "YLR231C", "YOR065W", "YGR183C", "YBR153W", "YNL247W", "YGL191W", "YFR033C", "YOL130W", "YAL023C", "Q0250", "YDL095W", "YPR191W", "YFR047C", "YLR130C", "YDL205C", "YOL066C", "YOL122C", "YER014W", "YKR052C", "YDR037W", "YDR044W", "YEL024W", "YCR034W", "YOR335C"], "OE": ["YOL052C", "YHR137W", "YPR118W", "YEL038W", "YLR017W", "YHR208W", "YJR024C", "YKL184W", "YMR009W", "YJR148W", "YPR069C", "YGL202W"]}, "exp": {"KD": ["YLR146C", "YMR020W", "YNL141W", "YPL052W", "YLR438W", "YJL088W", "YJR139C"], "OE": ["YOL052C", "YPR069C", "YDR502C", "YJR148W", "YLR017W", "YML022W", "YKL174C", "YOL061W", "YKL184W", "YOR130C", "YPR021C", "YOR375C"]}}